README.txt
setup.py
MiscLib/Combinators.py
MiscLib/DomHelpers.py
MiscLib/Functions.py
MiscLib/NetUtils.py
MiscLib/ScanDirectories.py
MiscLib/ScanFiles.py
MiscLib/SuperGlobal.py
MiscLib/TestUtils.py
MiscLib/__init__.py
MiscLib/tests/TestAll.py
MiscLib/tests/TestCombinators.py
MiscLib/tests/TestDomHelpers.py
MiscLib/tests/TestFunctions.py
MiscLib/tests/TestNetUtils.py
MiscLib/tests/TestScanDirectories.py
MiscLib/tests/TestScanFiles.py
MiscLib/tests/TestSuperGlobal.py
MiscLib/tests/TestTestUtils.py
MiscLib/tests/__init__.py
asqc/SparqlHttpClient.py
asqc/SparqlXmlResults.py
asqc/StdinContext.py
asqc/StdoutContext.py
asqc/__init__.py
asqc/asqc.py
asqc.egg-info/PKG-INFO
asqc.egg-info/SOURCES.txt
asqc.egg-info/dependency_links.txt
asqc.egg-info/entry_points.txt
asqc.egg-info/not-zip-safe
asqc.egg-info/requires.txt
asqc.egg-info/top_level.txt