Metadata-Version: 1.0
Name: asqc
Version: 0.1.7
Summary: A SPARQL Query Client
Home-page: https://github.com/gklyne/asqc
Author: Graham Klyne
Author-email: gk-pypi@ninebynine.org
License: MIT
Platform: UNKNOWN
Classifier: Development Status :: 3 - Alpha
Classifier: Environment :: Console
Classifier: Environment :: Web Environment
Classifier: Intended Audience :: Developers
Classifier: License :: OSI Approved :: MIT License
Classifier: Operating System :: OS Independent
Classifier: Programming Language :: Python
